cmtb/__init__.py
cmtb/confusion_matrix_tensorboard.py
cmtb-0.0.5.dist-info/LICENSE
cmtb-0.0.5.dist-info/METADATA
cmtb-0.0.5.dist-info/WHEEL
cmtb-0.0.5.dist-info/top_level.txt
cmtb-0.0.5.dist-info/RECORD
