Metadata-Version: 2.1
Name: cmtb
Version: 0.0.5
Summary: Confusion matrix in tensorboard
Home-page: https://github.com/mr-francois/cmtb
Author-email: mr.francois@gmx.de
License-File: LICENSE
Requires-Dist: tensorflow
Requires-Dist: numpy
Requires-Dist: sklearn
Requires-Dist: matplotlib
